vertexregen_tokenizer/__init__.py
vertexregen_tokenizer/__init__.pyi
vertexregen_tokenizer/_vertexregen_tokenizer_pybind.cpython-310-x86_64-linux-gnu.so
vertexregen_tokenizer/collapse.py
vertexregen_tokenizer/tokenize.py
vertexregen_tokenizer/utils.py
vertexregen_tokenizer.libs/libgmp-d944b113.so.10.3.2
vertexregen_tokenizer.libs/libgmpxx-8b3a383a.so.4.5.2
vertexregen_tokenizer.libs/libmpfr-b7fafdf8.so.4.1.6
vertexregen_tokenizer-0.0.2.dist-info/METADATA
vertexregen_tokenizer-0.0.2.dist-info/WHEEL
vertexregen_tokenizer-0.0.2.dist-info/RECORD
vertexregen_tokenizer-0.0.2.dist-info/sboms/auditwheel.cdx.json
