Metadata-Version: 2.4
Name: vertexregen_tokenizer
Version: 0.0.2
Summary: Tokenizer for VertexRegen
Author-Email: Xiang Zhang <xiz102@ucsd.edu>
License-Expression: MIT
Requires-Python: >=3.8
Requires-Dist: numpy>=1.20.0
